pandas_type_detector/__init__.py
pandas_type_detector/type_detector.py
pandas_type_detector-1.0.1.dist-info/LICENSE
pandas_type_detector-1.0.1.dist-info/METADATA
pandas_type_detector-1.0.1.dist-info/WHEEL
pandas_type_detector-1.0.1.dist-info/RECORD
