Metadata-Version: 2.3
Name: pandas-type-detector
Version: 1.0.1
Summary: Intelligent DataFrame type detection with sophisticated locale-aware parsing, confidence scoring, and smart text filtering
Keywords: pandas,dataframe,type-detection,data-cleaning,locale,pt-br,excel,confidence-scoring,text-filtering
Author: Joao Brito
Requires-Python: >=3.7
Classifier: Development Status :: 5 - Production/Stable
Classifier: Intended Audience :: Developers
Classifier: License :: OSI Approved :: MIT License
Classifier: Operating System :: OS Independent
Classifier: Programming Language :: Python :: 3
Classifier: Programming Language :: Python :: 3.7
Classifier: Programming Language :: Python :: 3.8
Classifier: Programming Language :: Python :: 3.9
Classifier: Programming Language :: Python :: 3.10
Classifier: Programming Language :: Python :: 3.11
Classifier: Programming Language :: Python :: 3.12
Classifier: Topic :: Software Development :: Libraries :: Python Modules
Classifier: Topic :: Scientific/Engineering :: Information Analysis
Classifier: Topic :: Utilities
Provides-Extra: dev
Requires-Dist: flake8 ; extra == "dev"
Requires-Dist: mypy ; extra == "dev"
Requires-Dist: numpy (>=1.19.0)
Requires-Dist: pandas (>=1.0.0)
Requires-Dist: pytest (>=6.0) ; extra == "dev"
Project-URL: Homepage, https://github.com/machado000/pandas-type-detector
Project-URL: Issues, https://github.com/machado000/pandas-type-detector/issues
